mcp_server_browser_use/__init__.py
mcp_server_browser_use/__main__.py
mcp_server_browser_use/run_agents.py
mcp_server_browser_use/server.py
mcp_server_browser_use/agent/__init__.py
mcp_server_browser_use/agent/custom_agent.py
mcp_server_browser_use/agent/custom_message_manager.py
mcp_server_browser_use/agent/custom_prompts.py
mcp_server_browser_use/agent/custom_system_prompt.md
mcp_server_browser_use/agent/custom_views.py
mcp_server_browser_use/browser/__init__.py
mcp_server_browser_use/browser/custom_browser.py
mcp_server_browser_use/browser/custom_context.py
mcp_server_browser_use/controller/__init__.py
mcp_server_browser_use/controller/custom_controller.py
mcp_server_browser_use/utils/__init__.py
mcp_server_browser_use/utils/agent_state.py
mcp_server_browser_use/utils/deep_research.py
mcp_server_browser_use/utils/llm.py
mcp_server_browser_use/utils/utils.py
nm_browser_use_mcp_server-0.1.13.dist-info/licenses/LICENSE
nm_browser_use_mcp_server-0.1.13.dist-info/METADATA
nm_browser_use_mcp_server-0.1.13.dist-info/WHEEL
nm_browser_use_mcp_server-0.1.13.dist-info/entry_points.txt
nm_browser_use_mcp_server-0.1.13.dist-info/top_level.txt
nm_browser_use_mcp_server-0.1.13.dist-info/RECORD
