Metadata-Version: 2.4
Name: nm-browser-use-mcp-server
Version: 0.1.13
Summary: MCP server for browser-use
Author: Igor Tarasenko
License: MIT
Requires-Python: >=3.11
License-File: LICENSE
Requires-Dist: langchain>=0.3.14
Requires-Dist: langchain-openai>=0.2.14
Requires-Dist: pydantic>=2.10.5
Requires-Dist: openai>=1.59.5
Requires-Dist: pyperclip>=1.9.0
Requires-Dist: langchain-ollama>=0.2.2
Requires-Dist: instructor>=1.7.2
Requires-Dist: json-repair>=0.35.0
Requires-Dist: langchain-mistralai>=0.2.6
Requires-Dist: mcp>=1.6.0
Requires-Dist: browser-use==0.1.40
Requires-Dist: MainContentExtractor==0.0.4
Requires-Dist: langchain-google-genai>=2.0.8
Requires-Dist: langchain-anthropic>=0.2.1
Requires-Dist: langchain-mistralai>=0.2.4
Requires-Dist: pillow>=11.1.0
Requires-Dist: lxml-html-clean>=0.4.2
Requires-Dist: playwright>=1.51.0
Dynamic: license-file
